Workbook

Sheet 00_Instruções
A1: Planilha de Precificação — Manual de Uso
A2: Modelo bottom-up baseado em custos do estúdio, horas por estágio e complexidade do projeto
A4: Fluxo de uso
A5: 1. Custos do Estúdio | B5: Preencha custos fixos mensais (aluguel, software, etc.) na aba 01. Define overhead/hora.
A6: 2. Custo-hora por Papel | B6: Preencha salários, encargos e horas faturáveis por papel na aba 02. Calcula tarifa/hora.
A7: 3. Horas Base por Estágio | B7: Calibrar a aba 03 com horas típicas para um projeto baseline. Use seus projetos anteriores como referência.
A8: 4. Complexidade do Projeto | B8: Para cada novo projeto, preencher scores 1-5 na aba 04. Resulta em multiplicador.
A9: 5. Configurador | B9: Marcar quais estágios estão contratados na aba 05. Calcula preço final.
A10: 6. Cenários | B10: A aba 06 mostra cenários típicos lado a lado para negociação.
A13: Convenções de cor
A14: Texto azul + fundo amarelo claro | B14: Input — célula que você edita
A15: Texto preto | B15: Fórmula calculada na mesma aba
A16: Texto verde | B16: Referência a outra aba (não editar)
A17: Fundo laranja claro | B17: Totais e resultados-chave
A18: Fundo amarelo médio | B18: Assumption crítica — calibrar com cuidado
A21: Notas metodológicas
A22: • | B22: Os valores default são placeholders e devem ser calibrados com os números reais do estúdio.
A23: • | B23: Overhead é distribuído sobre horas faturáveis efetivas (não sobre horas totais trabalhadas).
A24: • | B24: Complexidade afeta horas, não tarifa/hora. Lógica: projetos complexos demandam mais iteração, não cobrar caro pela hora.
A25: • | B25: Pacote completo (4-5 stages) aplica desconto de 10% sobre o subtotal — premiar contratação integral.
A26: • | B26: Stages contratados avulsos não recebem desconto — compensa overhead de setup não amortizado.
A27: • | B27: Impostos: configurar conforme regime tributário do estúdio (Simples Nacional, Lucro Presumido, etc.).
A28: • | B28: A planilha NÃO substitui análise caso a caso. Use como ponto de partida para discussão com o cliente.

Sheet 01_Custos_Estúdio
A1: Custos Fixos do Estúdio
A2: Inputs: custos fixos mensais. Output: overhead/hora produtiva.
A4: Despesas fixas mensais
B5: Item | C5: R$/mês | E5: Notas
B6: Aluguel + condomínio | C6: 0 | E6: Inclui IPTU
B7: Energia, internet, água, telefone | C7: 30
B8: Software (Revit, V-Ray, Office, Adobe...) | C8: 0 | E8: Licenças mensais e anuais rateadas
B9: Hardware (depreciação) | C9: 0 | E9: Workstations, monitores — depreciar em 36 meses
B10: Marketing e site | C10: 1000
B11: Contador / assessoria jurídica | C11: 86.05
B12: Educação continuada / treinamentos | C12: 100
B13: Outras despesas administrativas | C13: =4*190.53/12 -> 63.51
B14: TOTAL CUSTO FIXO MENSAL | C14: =SUM(C6:C13) -> 1279.56
A16: Capacidade produtiva do estúdio
B17: Dias úteis no mês | C17: 21
B18: Horas faturáveis/dia/pessoa | C18: 8
B19: Pessoas ativas no estúdio (média) | C19: 1
B20: TOTAL HORAS FATURÁVEIS/MÊS | C20: =C17*C18*C19 -> 168
A22: Cálculo do overhead
B23: OVERHEAD POR HORA FATURÁVEL | C23: =C14/C20 -> 7.6164286
B25: Esse valor é adicionado ao custo direto de cada hora trabalhada (aba 02). Garante que os custos fixos do estúdio sejam recuperados antes da margem.

Sheet 02_Custo_Hora_Papel
A1: Custo-Hora e Tarifa-Hora por Papel
A2: Inputs: salários, encargos, horas. Output: tarifa/hora a aplicar no orçamento.
A4: Configuração de remuneração e tarifa
B5: Margem-alvo (sobre custo total) | C5: 0.3
B6: Carga tributária (impostos sobre venda) | C6: 0
B8: Papel | C8: Salário Bruto | D8: Encargos | E8: Custo Total/mês | F8: Horas Faturáveis/mês | G8: Custo Direto/h | H8: Custo Total/h (com overhead) | I8: Tarifa/h
B9: Arquiteto Líder (RT) | C9: 6500 | D9: 0 | E9: =C9*(1+D9) -> 6500 | F9: 168 | G9: =E9/F9 -> 38.690476 | H9: =G9+'01_Custos_Estúdio'!$C$23 -> 46.306905 | I9: =H9*(1+$C$5)/(1-$C$6) -> 60.198976
B10: Coordenador de Projeto | C10: 0 | D10: 0 | E10: =C10*(1+D10) -> 0 | F10: 130 | G10: =E10/F10 -> 0 | H10: =G10+'01_Custos_Estúdio'!$C$23 -> 7.6164286 | I10: =H10*(1+$C$5)/(1-$C$6) -> 9.9013571
B11: Arquiteto Sênior | C11: 0 | D11: 0 | E11: =C11*(1+D11) -> 0 | F11: 140 | G11: =E11/F11 -> 0 | H11: =G11+'01_Custos_Estúdio'!$C$23 -> 7.6164286 | I11: =H11*(1+$C$5)/(1-$C$6) -> 9.9013571
B12: Arquiteto Pleno | C12: 0 | D12: 0 | E12: =C12*(1+D12) -> 0 | F12: 150 | G12: =E12/F12 -> 0 | H12: =G12+'01_Custos_Estúdio'!$C$23 -> 7.6164286 | I12: =H12*(1+$C$5)/(1-$C$6) -> 9.9013571
B13: Arquiteto Júnior | C13: 0 | D13: 0 | E13: =C13*(1+D13) -> 0 | F13: 160 | G13: =E13/F13 -> 0 | H13: =G13+'01_Custos_Estúdio'!$C$23 -> 7.6164286 | I13: =H13*(1+$C$5)/(1-$C$6) -> 9.9013571
B14: Coordenador BIM | C14: 0 | D14: 0 | E14: =C14*(1+D14) -> 0 | F14: 140 | G14: =E14/F14 -> 0 | H14: =G14+'01_Custos_Estúdio'!$C$23 -> 7.6164286 | I14: =H14*(1+$C$5)/(1-$C$6) -> 9.9013571
B15: Lead 3D / Visualização | C15: 0 | D15: 0 | E15: =C15*(1+D15) -> 0 | F15: 150 | G15: =E15/F15 -> 0 | H15: =G15+'01_Custos_Estúdio'!$C$23 -> 7.6164286 | I15: =H15*(1+$C$5)/(1-$C$6) -> 9.9013571
B16: Estagiário | C16: 0 | D16: 0 | E16: =C16*(1+D16) -> 0 | F16: 120 | G16: =E16/F16 -> 0 | H16: =G16+'01_Custos_Estúdio'!$C$23 -> 7.6164286 | I16: =H16*(1+$C$5)/(1-$C$6) -> 9.9013571
B18: Custo Total/h = Custo Direto/h + Overhead/h (da aba 01)
B19: Tarifa/h = Custo Total/h × (1+margem) / (1-impostos)

Sheet 03_Horas_Base_Estágio
A1: Horas Base por Estágio
A2: Esforço típico por papel/estágio em PROJETO BASELINE (residencial 300m², complexidade 1.0). Calibrar com históricos.
A4: Esforço (horas) por papel × estágio
B6: Papel | C6: Stage 0 Def. Estratégica | D6: Stage 1 Briefing | E6: Stage 2 Conceitual | F6: Stage 3 Anteprojeto | G6: Stage 4 P. Técnico | H6: TOTAL h | I6: TOTAL R$ (complex. 1.0)
B7: Arquiteto Líder (RT) | C7: 10 | D7: 10 | E7: 20 | F7: 20 | G7: 15 | H7: =SUM(C7:G7) -> 75 | I7: =H7*'02_Custo_Hora_Papel'!$I$9 -> 4514.9232
B8: Coordenador de Projeto | C8: 0 | D8: 0 | E8: 0 | F8: 0 | G8: 0 | H8: =SUM(C8:G8) -> 0 | I8: =H8*'02_Custo_Hora_Papel'!$I$10 -> 0
B9: Arquiteto Sênior | C9: 0 | D9: 0 | E9: 0 | F9: 0 | G9: 0 | H9: =SUM(C9:G9) -> 0 | I9: =H9*'02_Custo_Hora_Papel'!$I$11 -> 0
B10: Arquiteto Pleno | C10: 0 | D10: 0 | E10: 0 | F10: 0 | G10: 0 | H10: =SUM(C10:G10) -> 0 | I10: =H10*'02_Custo_Hora_Papel'!$I$12 -> 0
B11: Arquiteto Júnior | C11: 0 | D11: 0 | E11: 0 | F11: 0 | G11: 0 | H11: =SUM(C11:G11) -> 0 | I11: =H11*'02_Custo_Hora_Papel'!$I$13 -> 0
B12: Coordenador BIM | C12: 0 | D12: 0 | E12: 0 | F12: 0 | G12: 0 | H12: =SUM(C12:G12) -> 0 | I12: =H12*'02_Custo_Hora_Papel'!$I$14 -> 0
B13: Lead 3D / Visualização | C13: 0 | D13: 0 | E13: 0 | F13: 0 | G13: 0 | H13: =SUM(C13:G13) -> 0 | I13: =H13*'02_Custo_Hora_Papel'!$I$15 -> 0
B14: Estagiário | C14: 0 | D14: 0 | E14: 0 | F14: 0 | G14: 0 | H14: =SUM(C14:G14) -> 0 | I14: =H14*'02_Custo_Hora_Papel'!$I$16 -> 0
B15: TOTAL HORAS / ESTÁGIO | C15: =SUM(C7:C14) -> 10 | D15: =SUM(D7:D14) -> 10 | E15: =SUM(E7:E14) -> 20 | F15: =SUM(F7:F14) -> 20 | G15: =SUM(G7:G14) -> 15 | H15: =SUM(C15:G15) -> 75 | I15: =SUM(I7:I14) -> 4514.9232
B16: CUSTO TOTAL/ESTÁGIO (R$) | C16: =C7*'02_Custo_Hora_Papel'!$I$9+C8*'02_Custo_Hora_Papel'!$I$10+C9*'02_Custo_Hora_Papel'!$I$11+C10*'02_Custo_Hora_Papel'!$I$12+C11*'02_Custo_Hora_Papel'!$I$13+C12*'02_Custo_Hora_Papel'!$I$14+C13*'02_Custo_Hora_Papel'!$I$15+C14*'02_Custo_Hora_Papel'!$I$16 -> 601.98976 | D16: =D7*'02_Custo_Hora_Papel'!$I$9+D8*'02_Custo_Hora_Papel'!$I$10+D9*'02_Custo_Hora_Papel'!$I$11+D10*'02_Custo_Hora_Papel'!$I$12+D11*'02_Custo_Hora_Papel'!$I$13+D12*'02_Custo_Hora_Papel'!$I$14+D13*'02_Custo_Hora_Papel'!$I$15+D14*'02_Custo_Hora_Papel'!$I$16 -> 601.98976 | E16: =E7*'02_Custo_Hora_Papel'!$I$9+E8*'02_Custo_Hora_Papel'!$I$10+E9*'02_Custo_Hora_Papel'!$I$11+E10*'02_Custo_Hora_Papel'!$I$12+E11*'02_Custo_Hora_Papel'!$I$13+E12*'02_Custo_Hora_Papel'!$I$14+E13*'02_Custo_Hora_Papel'!$I$15+E14*'02_Custo_Hora_Papel'!$I$16 -> 1203.9795 | F16: =F7*'02_Custo_Hora_Papel'!$I$9+F8*'02_Custo_Hora_Papel'!$I$10+F9*'02_Custo_Hora_Papel'!$I$11+F10*'02_Custo_Hora_Papel'!$I$12+F11*'02_Custo_Hora_Papel'!$I$13+F12*'02_Custo_Hora_Papel'!$I$14+F13*'02_Custo_Hora_Papel'!$I$15+F14*'02_Custo_Hora_Papel'!$I$16 -> 1203.9795 | G16: =G7*'02_Custo_Hora_Papel'!$I$9+G8*'02_Custo_Hora_Papel'!$I$10+G9*'02_Custo_Hora_Papel'!$I$11+G10*'02_Custo_Hora_Papel'!$I$12+G11*'02_Custo_Hora_Papel'!$I$13+G12*'02_Custo_Hora_Papel'!$I$14+G13*'02_Custo_Hora_Papel'!$I$15+G14*'02_Custo_Hora_Papel'!$I$16 -> 902.98464
B18: Estas horas representam um projeto residencial baseline (~300m², complexidade 1.0). Calibre com o histórico do estúdio: olhe os 3-5 últimos projetos e ajuste.

Sheet 04_Complexidade
A1: Complexidade do Projeto
A2: Score 1-5 em 5 dimensões. Output: multiplicador a aplicar nas horas baseline.
A4: Fatores de complexidade (1 = simples / 5 = muito complexo)
B5: Dimensão | C5: Score (1-5) | D5: Referência rápida
B6: Tipologia | C6: 5 | D6: 1: residência simples / 3: comercial padrão / 5: hospital, laboratório, especializado
B7: Programa e escopo | C7: 5 | D7: 1: programa convencional / 3: programa misto / 5: programa altamente especializado
B8: Terreno | C8: 5 | D8: 1: plano regular urbano / 3: declive moderado / 5: topografia complexa, irregular, rural
B9: Regulatório | C9: 5 | D9: 1: zoneamento padrão / 3: zona especial / 5: tombamento + EIV + restrições múltiplas
B10: Ambição de design | C10: 5 | D10: 1: padrão funcional / 3: design diferenciado / 5: ícone, premium internacional
A12: Score composto e multiplicador
B13: Score médio | C13: =AVERAGE(C6:C10) -> 5
B14: MULTIPLICADOR DE HORAS | C14: =0.7+(C13-1)*0.2 -> 1.5
A16: Tabela de referência: score médio → multiplicador
B17: Score médio | C17: Multiplicador | D17: Interpretação
B18: 1 | C18: 0.70x | D18: Projeto muito simples — baixa exigência em todas dimensões
B19: 2 | C19: 0.90x | D19: Projeto simples — escopo bem definido, complexidade baixa
B20: 3 | C20: 1.10x | D20: Projeto padrão — complexidade média (referência típica)
B21: 4 | C21: 1.30x | D21: Projeto complexo — alta exigência em múltiplas dimensões
B22: 5 | C22: 1.50x | D22: Projeto muito complexo — extremo em todas dimensões
B24: O multiplicador é aplicado sobre as HORAS BASE (aba 03), não sobre a tarifa/hora. Lógica: projeto complexo demanda mais iteração, não cobrar mais por hora.

Sheet 05_Configurador
A1: Configurador de Cenário
A2: Selecione os estágios contratados. A planilha calcula horas, custo e preço final.
A4: Identificação do projeto
B5: Nome do projeto | C5: [Nome]
B6: Cliente | C6: [Cliente]
B7: Área (m²) | C7: 300
B8: Multiplicador de complexidade | C8: ='04_Complexidade'!$C$14 -> 1.5
A10: Configuração de estágios
B11: Estágio | C11: Contratado? (Sim/Não) | D11: Horas (base) | E11: Horas (× complex.) | F11: Custo Base R$ | G11: Custo Ajustado R$
B12: Stage 0 — Captação e Alinhamento | C12: Sim | D12: ='03_Horas_Base_Estágio'!C15 -> 10 | E12: =IF(C12="Sim",D12*$C$8,0) -> 15 | F12: ='03_Horas_Base_Estágio'!$C$16 -> 601.98976 | G12: =IF(C12="Sim",F12*$C$8,0) -> 902.98464
B13: Stage 1 — Briefing | C13: Sim | D13: ='03_Horas_Base_Estágio'!D15 -> 10 | E13: =IF(C13="Sim",D13*$C$8,0) -> 15 | F13: ='03_Horas_Base_Estágio'!$D$16 -> 601.98976 | G13: =IF(C13="Sim",F13*$C$8,0) -> 902.98464
B14: Stage 2 — Criação e Conceito | C14: Sim | D14: ='03_Horas_Base_Estágio'!E15 -> 20 | E14: =IF(C14="Sim",D14*$C$8,0) -> 30 | F14: ='03_Horas_Base_Estágio'!$E$16 -> 1203.9795 | G14: =IF(C14="Sim",F14*$C$8,0) -> 1805.9693
B15: Stage 3 — Detalhamento de Acabamentos | C15: Sim | D15: ='03_Horas_Base_Estágio'!F15 -> 20 | E15: =IF(C15="Sim",D15*$C$8,0) -> 30 | F15: ='03_Horas_Base_Estágio'!$F$16 -> 1203.9795 | G15: =IF(C15="Sim",F15*$C$8,0) -> 1805.9693
B16: Stage 4 — Executivo | C16: Sim | D16: ='03_Horas_Base_Estágio'!G15 -> 15 | E16: =IF(C16="Sim",D16*$C$8,0) -> 22.5 | F16: ='03_Horas_Base_Estágio'!$G$16 -> 902.98464 | G16: =IF(C16="Sim",F16*$C$8,0) -> 1354.477
B17: SUBTOTAL | E17: =SUM(E12:E16) -> 112.5 | G17: =SUM(G12:G16) -> 6772.3848
A19: Aplicação de desconto de pacote
B20: Estágios contratados | C20: =COUNTIF(C12:C16,"Sim") -> 5
B21: Modo de contratação | C21: =IF(C20>=4,"Pacote",IF(C20>=2,"Parcial","Avulso")) -> Pacote
B22: Desconto aplicado | C22: 0
B23: Valor do desconto | C23: =IF(C21="Pacote",G17*C22,0) -> 0
A25: PREÇO FINAL DE PROPOSTA
B26: Honorário total ao cliente | C26: =G17-C23 -> 6772.3848
B28: R$/m² implícito | C28: =C26/C7 -> 22.574616
B29: Horas totais | C29: =E17 -> 112.5
B30: R$/hora implícito | C30: =IF(E17>0,C26/E17,0) -> 60.198976

Sheet 06_Cenários_Comparativos
A1: Cenários Comparativos
A2: Cenários típicos de contratação lado a lado. Usar como base de negociação.
A4: Configuração dos cenários
B5: Multiplicador (usa aba 04) | C5: ='04_Complexidade'!$C$14 -> 1.5
B7: Métrica | C7: A — Pacote Completo | D7: B — Pacote sem Stage 0 | E7: C — Conceito → Executivo | F7: D — Conceito + Anteprojeto | G7: E — Anteprojeto + Executivo | H7: F — Só Executivo
B8: Stage 0 | C8: ● | D8: ○ | E8: ○ | F8: ● | G8: ○ | H8: ○
B9: Stage 1 | C9: ● | D9: ● | E9: ○ | F9: ● | G9: ○ | H9: ○
B10: Stage 2 | C10: ● | D10: ● | E10: ● | F10: ● | G10: ○ | H10: ○
B11: Stage 3 | C11: ● | D11: ● | E11: ● | F11: ● | G11: ● | H11: ○
B12: Stage 4 | C12: ● | D12: ● | E12: ● | F12: ○ | G12: ● | H12: ●
B14: Subtotal (com complex.) | C14: =('03_Horas_Base_Estágio'!$C$16+'03_Horas_Base_Estágio'!$D$16+'03_Horas_Base_Estágio'!$E$16+'03_Horas_Base_Estágio'!$F$16+'03_Horas_Base_Estágio'!$G$16)*$C$5 -> 6772.3848 | D14: =('03_Horas_Base_Estágio'!$D$16+'03_Horas_Base_Estágio'!$E$16+'03_Horas_Base_Estágio'!$F$16+'03_Horas_Base_Estágio'!$G$16)*$C$5 -> 5869.4002 | E14: =('03_Horas_Base_Estágio'!$E$16+'03_Horas_Base_Estágio'!$F$16+'03_Horas_Base_Estágio'!$G$16)*$C$5 -> 4966.4155 | F14: =('03_Horas_Base_Estágio'!$C$16+'03_Horas_Base_Estágio'!$D$16+'03_Horas_Base_Estágio'!$E$16)*$C$5 -> 3611.9386 | G14: =('03_Horas_Base_Estágio'!$F$16+'03_Horas_Base_Estágio'!$G$16)*$C$5 -> 3160.4462 | H14: =('03_Horas_Base_Estágio'!$G$16)*$C$5 -> 1354.477
B15: # Stages contratados | C15: 5 | D15: 4 | E15: 3 | F15: 4 | G15: 2 | H15: 1
B16: Desconto pacote (10% se ≥4) | C16: =IF(C15>=4,C14*0.1,0) -> 677.23848 | D16: =IF(D15>=4,D14*0.1,0) -> 586.94002 | E16: =IF(E15>=4,E14*0.1,0) -> 0 | F16: =IF(F15>=4,F14*0.1,0) -> 361.19386 | G16: =IF(G15>=4,G14*0.1,0) -> 0 | H16: =IF(H15>=4,H14*0.1,0) -> 0
B17: PREÇO FINAL | C17: =C14-C16 -> 6095.1463 | D17: =D14-D16 -> 5282.4602 | E17: =E14-E16 -> 4966.4155 | F17: =F14-F16 -> 3250.7447 | G17: =G14-G16 -> 3160.4462 | H17: =H14-H16 -> 1354.477
B19: % vs Cenário A | C19: =C17/$C$17 -> 1 | D19: =D17/$C$17 -> 0.86666667 | E19: =E17/$C$17 -> 0.81481481 | F19: =F17/$C$17 -> 0.53333333 | G19: =G17/$C$17 -> 0.51851852 | H19: =H17/$C$17 -> 0.22222222
A21: Descrição dos cenários
B22: A — Pacote Completo | C22: Stages 0-4 — Projeto novo (arquitetura, interiores e reforma)
B23: B — Cliente Antigo, Novo Projeto | C23: Stages 1-4 — Clientes que já fecharam com o Studio antes e estão voltando para um novo projeto
B24: C — Um briefing, Dois projetos | C24: Stages 2-4 — Cliente com mais de um apartamento seguindo o mesmo projeto (perfil investidor; 1 briefing para dois projetos)
B25: D — Consultoria | C25: Stages 2-3 — Consultoria (projeto conceitual, mais simplificado)
B26: E — Executivo + Memorial | C26: Stages 3-4 — Detalhamento e desenhos técnicos para projeto executivo a partir de um projeto de outro escritório sem memorial de acabamentos definidos
B27: F — Executivo Completo | C27: Stage 4 — Detalhamento e desenhos técnicos para projeto executivo a partir de um projeto de outro escritório com memorial de acabamentos definidos
A30: Notas de uso comercial
B31: • | C31: Cenário A é a oferta-âncora — mostre primeiro para ancorar o cliente no valor total.
B32: • | C32: Cliente que pede só Stage 4 (Cenário F): negocie incluir Stage 3 — sem anteprojeto coordenado, o executivo vira lambança.
B33: • | C33: Cliente que pede só conceito (Cenário D): cuidado com transferência de IP. Garantir cláusula de uso.
B34: • | C34: Cenário B é o mais comum para clientes com algum nível de maturidade — vale defaultar para ele.
B35: • | C35: Se o cliente não fecha com A mas fecha com B, B + extras (acompanhamento de obra, viz extra) pode chegar ao mesmo valor.
